source_firebolt/__init__.py
source_firebolt/database.py
source_firebolt/run.py
source_firebolt/source.py
source_firebolt/spec.json
source_firebolt/utils.py
airbyte_source_firebolt-2.0.39.dist-info/METADATA
airbyte_source_firebolt-2.0.39.dist-info/WHEEL
airbyte_source_firebolt-2.0.39.dist-info/entry_points.txt
airbyte_source_firebolt-2.0.39.dist-info/RECORD
