Metadata-Version: 2.1
Name: airbyte-source-firebolt
Version: 2.0.39
Summary: Source implementation for Firebolt.
Home-page: https://airbyte.com
License: MIT
Author: Airbyte
Author-email: contact@airbyte.io
Requires-Python: >=3.9,<3.12
Classifier: License :: OSI Approved :: MIT License
Classifier: Programming Language :: Python :: 3
Classifier: Programming Language :: Python :: 3.9
Classifier: Programming Language :: Python :: 3.10
Classifier: Programming Language :: Python :: 3.11
Requires-Dist: airbyte-cdk (>=0,<1)
Requires-Dist: firebolt-sdk (>=1.1.0,<2.0.0)
Project-URL: Documentation, https://docs.airbyte.com/integrations/sources/firebolt
Project-URL: Repository, https://github.com/airbytehq/airbyte
